vista.py
src/__init__.py
src/adaptive_parameters.py
src/advanced_patterns.py
src/alpha_signals.py
src/backtest.py
src/bracket_orders.py
src/chart_analysis.py
src/chart_scheduler.py
src/database.py
src/discord_notifier.py
src/hyperliquid_client.py
src/learning_engine.py
src/llm_service.py
src/micro_intelligence.py
src/ml_learning.py
src/orderbook_analyzer.py
src/pattern_detector.py
src/performance_tracker.py
src/proactive_micro.py
src/realtime_monitor.py
src/signal_aggregator.py
src/signal_learning.py
src/smart_money_concepts.py
src/sniper.py
src/technical_analysis.py
src/tickers.py
src/trading_bot.py
src/vista_auth.py
src/vista_config.py
src/vista_dashboard.py
src/vista_setup.py
src/volume_profile.py
src/whale_data_collector.py
src/whale_ml_model.py
src/whale_ml_scheduler.py
vista_trading-0.1.1.dist-info/METADATA
vista_trading-0.1.1.dist-info/WHEEL
vista_trading-0.1.1.dist-info/entry_points.txt
vista_trading-0.1.1.dist-info/top_level.txt
vista_trading-0.1.1.dist-info/RECORD
