Metadata-Version: 2.4
Name: vista-trading
Version: 0.1.1
Summary: AI-powered crypto trading terminal for Hyperliquid
Author-email: Vista <hello@vista.trading>
License: MIT
Project-URL: Homepage, https://github.com/dotkoms/trading-bot
Project-URL: Documentation, https://github.com/dotkoms/trading-bot#readme
Project-URL: Repository, https://github.com/dotkoms/trading-bot
Project-URL: Issues, https://github.com/dotkoms/trading-bot/issues
Keywords: crypto,trading,hyperliquid,ai,terminal,cli
Classifier: Development Status :: 4 - Beta
Classifier: Environment :: Console
Classifier: Intended Audience :: Financial and Insurance Industry
Classifier: License :: OSI Approved :: MIT License
Classifier: Operating System :: OS Independent
Classifier: Programming Language :: Python :: 3
Classifier: Programming Language :: Python :: 3.9
Classifier: Programming Language :: Python :: 3.10
Classifier: Programming Language :: Python :: 3.11
Classifier: Programming Language :: Python :: 3.12
Classifier: Topic :: Office/Business :: Financial :: Investment
Requires-Python: >=3.9
Requires-Dist: rich>=13.0.0
Requires-Dist: httpx>=0.24.0
Requires-Dist: openai>=1.0.0
Requires-Dist: plotext>=5.2.0
Requires-Dist: python-dotenv>=1.0.0
Requires-Dist: websockets>=11.0.0
Requires-Dist: eth-account>=0.9.0
Provides-Extra: dev
Requires-Dist: pytest>=7.0.0; extra == "dev"
Requires-Dist: pytest-asyncio>=0.21.0; extra == "dev"
Requires-Dist: black>=23.0.0; extra == "dev"
Requires-Dist: ruff>=0.1.0; extra == "dev"
